{
	"name": "Zombie",
	"plugin-id": "Sprite",
	"sid": 760438711424614,
	"isGlobal": false,
	"instanceVariables": [
		{
			"name": "direction",
			"type": "number",
			"desc": "",
			"sid": 625826748366631
		},
		{
			"name": "attacking",
			"type": "boolean",
			"desc": "",
			"sid": 227156691691542
		},
		{
			"name": "chargingUp",
			"type": "boolean",
			"desc": "",
			"sid": 397376903308003
		},
		{
			"name": "anim",
			"type": "string",
			"desc": "",
			"sid": 733847543682843
		},
		{
			"name": "attackPause",
			"type": "boolean",
			"desc": "",
			"sid": 269013814127148
		},
		{
			"name": "invincible",
			"type": "boolean",
			"desc": "",
			"sid": 157578953611126
		},
		{
			"name": "health",
			"type": "number",
			"desc": "",
			"sid": 534340051185701
		},
		{
			"name": "Creature",
			"type": "string",
			"desc": "",
			"sid": 682728025220739
		},
		{
			"name": "Size",
			"type": "number",
			"desc": "",
			"sid": 954964007414861
		},
		{
			"name": "AttackRangeModifier",
			"type": "number",
			"desc": "",
			"sid": 308274620112490
		},
		{
			"name": "AttackSpeed",
			"type": "number",
			"desc": "",
			"sid": 539855911195296
		},
		{
			"name": "AttackLength",
			"type": "number",
			"desc": "",
			"sid": 171060280383186
		},
		{
			"name": "ChargeTime",
			"type": "number",
			"desc": "",
			"sid": 371854455223696
		}
	],
	"behaviorTypes": [
		{
			"behaviorId": "TileMovement",
			"name": "TileMovement",
			"sid": 340439180166684
		},
		{
			"behaviorId": "bound",
			"name": "BoundToLayout",
			"sid": 163500904567789
		},
		{
			"behaviorId": "solid",
			"name": "Solid",
			"sid": 448722385254490
		}
	],
	"effectTypes": [],
	"animations": {
		"items": [
			{
				"frames": [
					{
						"width": 128,
						"height": 128,
						"originX": 0.5,
						"originY": 0.5,
						"originalSource": "",
						"exportFormat": "png",
						"exportQuality": 0.8,
						"imageSpriteId": 6114029,
						"collisionPoly": {
							"points": [
								0.28125,
								0.28125,
								0.5,
								0.125,
								0.7177734375,
								0.28125,
								0.8427734375,
								0.5,
								0.7802734375,
								0.7802734375,
								0.5,
								0.7490234375,
								0.21875,
								0.7802734375,
								0.15625,
								0.5
							]
						},
						"useCollisionPoly": true,
						"duration": 1
					},
					{
						"width": 128,
						"height": 128,
						"originX": 0.5,
						"originY": 0.5,
						"originalSource": "",
						"exportFormat": "png",
						"exportQuality": 0.8,
						"imageSpriteId": 242699,
						"collisionPoly": {
							"points": [
								0.28125,
								0.28125,
								0.5,
								0.125,
								0.7177734375,
								0.28125,
								0.8427734375,
								0.5,
								0.6552734375,
								0.6552734375,
								0.5,
								0.7490234375,
								0.21875,
								0.7802734375,
								0.15625,
								0.5
							]
						},
						"useCollisionPoly": true,
						"duration": 1
					},
					{
						"width": 128,
						"height": 128,
						"originX": 0.5,
						"originY": 0.5,
						"originalSource": "",
						"exportFormat": "png",
						"exportQuality": 0.8,
						"imageSpriteId": 8121662,
						"collisionPoly": {
							"points": [
								0.28125,
								0.28125,
								0.5,
								0.125,
								0.7177734375,
								0.28125,
								0.8427734375,
								0.5,
								0.7802734375,
								0.7802734375,
								0.5,
								0.7490234375,
								0.21875,
								0.7802734375,
								0.15625,
								0.5
							]
						},
						"useCollisionPoly": true,
						"duration": 1
					},
					{
						"width": 128,
						"height": 128,
						"originX": 0.5,
						"originY": 0.5,
						"originalSource": "",
						"exportFormat": "png",
						"exportQuality": 0.8,
						"imageSpriteId": 1558720,
						"collisionPoly": {
							"points": [
								0.28125,
								0.28125,
								0.5,
								0.125,
								0.7177734375,
								0.28125,
								0.8427734375,
								0.5,
								0.7802734375,
								0.7802734375,
								0.5,
								0.7490234375,
								0.34375,
								0.6552734375,
								0.15625,
								0.5
							]
						},
						"useCollisionPoly": true,
						"duration": 1
					}
				],
				"sid": 491725964205958,
				"name": "Zombie_South",
				"isLooping": true,
				"isPingPong": false,
				"repeatCount": 1,
				"repeatTo": 0,
				"speed": 5
			},
			{
				"frames": [
					{
						"width": 128,
						"height": 128,
						"originX": 0.5,
						"originY": 0.5,
						"originalSource": "",
						"exportFormat": "png",
						"exportQuality": 0.8,
						"imageSpriteId": 8993560,
						"collisionPoly": {
							"points": [
								0.25,
								0.25,
								0.5,
								0.0625,
								0.5615234375,
								0.4375,
								0.6865234375,
								0.5,
								0.6865234375,
								0.6865234375,
								0.5,
								0.8740234375,
								0.375,
								0.6240234375,
								0.3125,
								0.5
							]
						},
						"useCollisionPoly": true,
						"duration": 1
					},
					{
						"width": 128,
						"height": 128,
						"originX": 0.5,
						"originY": 0.5,
						"originalSource": "",
						"exportFormat": "png",
						"exportQuality": 0.8,
						"imageSpriteId": 3464049,
						"collisionPoly": {
							"points": [
								0.25,
								0.25,
								0.5,
								0.0625,
								0.5615234375,
								0.4375,
								0.6865234375,
								0.5,
								0.6865234375,
								0.6865234375,
								0.5,
								0.8115234375,
								0.375,
								0.6240234375,
								0.3125,
								0.5
							]
						},
						"useCollisionPoly": true,
						"duration": 1
					},
					{
						"width": 128,
						"height": 128,
						"originX": 0.5,
						"originY": 0.5,
						"originalSource": "",
						"exportFormat": "png",
						"exportQuality": 0.8,
						"imageSpriteId": 7418508,
						"collisionPoly": {
							"points": [
								0.25,
								0.25,
								0.5,
								0.0625,
								0.5615234375,
								0.4375,
								0.6865234375,
								0.5,
								0.6865234375,
								0.6865234375,
								0.5,
								0.8740234375,
								0.375,
								0.6240234375,
								0.3125,
								0.5
							]
						},
						"useCollisionPoly": true,
						"duration": 1
					},
					{
						"width": 128,
						"height": 128,
						"originX": 0.5,
						"originY": 0.5,
						"originalSource": "",
						"exportFormat": "png",
						"exportQuality": 0.8,
						"imageSpriteId": 6169295,
						"collisionPoly": {
							"points": [
								0.25,
								0.25,
								0.5,
								0.0625,
								0.5615234375,
								0.4375,
								0.6865234375,
								0.5,
								0.6865234375,
								0.6865234375,
								0.5,
								0.8740234375,
								0.25,
								0.7490234375,
								0.3125,
								0.5
							]
						},
						"useCollisionPoly": true,
						"duration": 1
					}
				],
				"sid": 486383161238765,
				"name": "Zombie_East",
				"isLooping": true,
				"isPingPong": false,
				"repeatCount": 1,
				"repeatTo": 0,
				"speed": 5
			},
			{
				"frames": [
					{
						"width": 128,
						"height": 128,
						"originX": 0.5,
						"originY": 0.5,
						"originalSource": "",
						"exportFormat": "png",
						"exportQuality": 0.8,
						"imageSpriteId": 4055637,
						"collisionPoly": {
							"points": [
								0.28125,
								0.28125,
								0.5,
								0.125,
								0.7177734375,
								0.28125,
								0.8427734375,
								0.5,
								0.7802734375,
								0.7802734375,
								0.5,
								0.7490234375,
								0.21875,
								0.7802734375,
								0.15625,
								0.5
							]
						},
						"useCollisionPoly": true,
						"duration": 1
					},
					{
						"width": 128,
						"height": 128,
						"originX": 0.5,
						"originY": 0.5,
						"originalSource": "",
						"exportFormat": "png",
						"exportQuality": 0.8,
						"imageSpriteId": 4023282,
						"collisionPoly": {
							"points": [
								0.28125,
								0.28125,
								0.5,
								0.125,
								0.7177734375,
								0.28125,
								0.8427734375,
								0.5,
								0.6552734375,
								0.6552734375,
								0.5,
								0.7490234375,
								0.21875,
								0.7802734375,
								0.15625,
								0.5
							]
						},
						"useCollisionPoly": true,
						"duration": 1
					},
					{
						"width": 128,
						"height": 128,
						"originX": 0.5,
						"originY": 0.5,
						"originalSource": "",
						"exportFormat": "png",
						"exportQuality": 0.8,
						"imageSpriteId": 5741084,
						"collisionPoly": {
							"points": [
								0.28125,
								0.28125,
								0.5,
								0.125,
								0.7177734375,
								0.28125,
								0.8427734375,
								0.5,
								0.7802734375,
								0.7802734375,
								0.5,
								0.7490234375,
								0.21875,
								0.7802734375,
								0.15625,
								0.5
							]
						},
						"useCollisionPoly": true,
						"duration": 1
					},
					{
						"width": 128,
						"height": 128,
						"originX": 0.5,
						"originY": 0.5,
						"originalSource": "",
						"exportFormat": "png",
						"exportQuality": 0.8,
						"imageSpriteId": 5351895,
						"collisionPoly": {
							"points": [
								0.28125,
								0.28125,
								0.5,
								0.125,
								0.7177734375,
								0.28125,
								0.8427734375,
								0.5,
								0.7802734375,
								0.7802734375,
								0.5,
								0.7490234375,
								0.34375,
								0.6552734375,
								0.15625,
								0.5
							]
						},
						"useCollisionPoly": true,
						"duration": 1
					}
				],
				"sid": 473769125674040,
				"name": "Zombie_North",
				"isLooping": true,
				"isPingPong": false,
				"repeatCount": 1,
				"repeatTo": 0,
				"speed": 5
			},
			{
				"frames": [
					{
						"width": 128,
						"height": 128,
						"originX": 0.5,
						"originY": 0.5,
						"originalSource": "",
						"exportFormat": "png",
						"exportQuality": 0.8,
						"imageSpriteId": 944174,
						"collisionPoly": {
							"points": [
								0.4375,
								0.4375,
								0.5,
								0.0625,
								0.7490234375,
								0.25,
								0.6865234375,
								0.5,
								0.6240234375,
								0.6240234375,
								0.5,
								0.8740234375,
								0.3125,
								0.6865234375,
								0.3125,
								0.5
							]
						},
						"useCollisionPoly": true,
						"duration": 1
					},
					{
						"width": 128,
						"height": 128,
						"originX": 0.5,
						"originY": 0.5,
						"originalSource": "",
						"exportFormat": "png",
						"exportQuality": 0.8,
						"imageSpriteId": 8298863,
						"collisionPoly": {
							"points": [
								0.4375,
								0.4375,
								0.5,
								0.0625,
								0.7490234375,
								0.25,
								0.6865234375,
								0.5,
								0.6240234375,
								0.6240234375,
								0.5,
								0.8740234375,
								0.3125,
								0.6865234375,
								0.3125,
								0.5
							]
						},
						"useCollisionPoly": true,
						"duration": 1
					},
					{
						"width": 128,
						"height": 128,
						"originX": 0.5,
						"originY": 0.5,
						"originalSource": "",
						"exportFormat": "png",
						"exportQuality": 0.8,
						"imageSpriteId": 5938361,
						"collisionPoly": {
							"points": [
								0.4375,
								0.4375,
								0.5,
								0.0625,
								0.7490234375,
								0.25,
								0.6865234375,
								0.5,
								0.6240234375,
								0.6240234375,
								0.5,
								0.8740234375,
								0.3125,
								0.6865234375,
								0.3125,
								0.5
							]
						},
						"useCollisionPoly": true,
						"duration": 1
					},
					{
						"width": 128,
						"height": 128,
						"originX": 0.5,
						"originY": 0.5,
						"originalSource": "",
						"exportFormat": "png",
						"exportQuality": 0.8,
						"imageSpriteId": 467052,
						"collisionPoly": {
							"points": [
								0.4375,
								0.4375,
								0.5,
								0.0625,
								0.7490234375,
								0.25,
								0.6865234375,
								0.5,
								0.7490234375,
								0.7490234375,
								0.5,
								0.8115234375,
								0.3125,
								0.6865234375,
								0.3125,
								0.5
							]
						},
						"useCollisionPoly": true,
						"duration": 1
					}
				],
				"sid": 209013712367533,
				"name": "Zombie_West",
				"isLooping": true,
				"isPingPong": false,
				"repeatCount": 1,
				"repeatTo": 0,
				"speed": 5
			},
			{
				"frames": [
					{
						"width": 128,
						"height": 128,
						"originX": 0.5,
						"originY": 0.5,
						"originalSource": "",
						"exportFormat": "png",
						"exportQuality": 0.8,
						"imageSpriteId": 4329006,
						"collisionPoly": {
							"points": [
								0.28125,
								0.28125,
								0.5,
								0.125,
								0.7177734375,
								0.28125,
								0.8427734375,
								0.5,
								0.7802734375,
								0.7802734375,
								0.5,
								0.7490234375,
								0.21875,
								0.7802734375,
								0.15625,
								0.5
							]
						},
						"useCollisionPoly": true,
						"duration": 1
					},
					{
						"width": 128,
						"height": 128,
						"originX": 0.5,
						"originY": 0.5,
						"originalSource": "",
						"exportFormat": "png",
						"exportQuality": 0.8,
						"imageSpriteId": 6470934,
						"collisionPoly": {
							"points": [
								0.25,
								0.25,
								0.5,
								0.0625,
								0.5615234375,
								0.4375,
								0.6865234375,
								0.5,
								0.6240234375,
								0.6240234375,
								0.5,
								0.8740234375,
								0.375,
								0.6240234375,
								0.3125,
								0.5
							]
						},
						"useCollisionPoly": true,
						"duration": 1
					},
					{
						"width": 128,
						"height": 128,
						"originX": 0.5,
						"originY": 0.5,
						"originalSource": "",
						"exportFormat": "png",
						"exportQuality": 0.8,
						"imageSpriteId": 1942862,
						"collisionPoly": {
							"points": [
								0.28125,
								0.28125,
								0.5,
								0.125,
								0.7177734375,
								0.28125,
								0.8427734375,
								0.5,
								0.7802734375,
								0.7802734375,
								0.5,
								0.7490234375,
								0.21875,
								0.7802734375,
								0.15625,
								0.5
							]
						},
						"useCollisionPoly": true,
						"duration": 1
					},
					{
						"width": 128,
						"height": 128,
						"originX": 0.5,
						"originY": 0.5,
						"originalSource": "",
						"exportFormat": "png",
						"exportQuality": 0.8,
						"imageSpriteId": 2000155,
						"collisionPoly": {
							"points": [
								0.4375,
								0.4375,
								0.5,
								0.0625,
								0.7490234375,
								0.25,
								0.6865234375,
								0.5,
								0.6240234375,
								0.6240234375,
								0.5,
								0.8740234375,
								0.375,
								0.6240234375,
								0.3125,
								0.5
							]
						},
						"useCollisionPoly": true,
						"duration": 1
					}
				],
				"sid": 723450427681604,
				"name": "Zombie_Charge",
				"isLooping": false,
				"isPingPong": false,
				"repeatCount": 1,
				"repeatTo": 0,
				"speed": 0
			},
			{
				"frames": [
					{
						"width": 128,
						"height": 128,
						"originX": 0.5,
						"originY": 0.5,
						"originalSource": "",
						"exportFormat": "png",
						"exportQuality": 0.8,
						"imageSpriteId": 5899811,
						"collisionPoly": {
							"points": [
								0.28125,
								0.28125,
								0.5,
								0.125,
								0.7177734375,
								0.28125,
								0.9052734375,
								0.5,
								0.7802734375,
								0.7802734375,
								0.5,
								0.7490234375,
								0.21875,
								0.7802734375,
								0.09375,
								0.5
							]
						},
						"useCollisionPoly": true,
						"duration": 1
					},
					{
						"width": 128,
						"height": 128,
						"originX": 0.5,
						"originY": 0.5,
						"originalSource": "",
						"exportFormat": "png",
						"exportQuality": 0.8,
						"imageSpriteId": 9553877,
						"collisionPoly": {
							"points": [
								0.25,
								0.25,
								0.5,
								0.0625,
								0.5615234375,
								0.4375,
								0.6865234375,
								0.5,
								0.6865234375,
								0.6865234375,
								0.5,
								0.8740234375,
								0.375,
								0.6240234375,
								0.3125,
								0.5
							]
						},
						"useCollisionPoly": true,
						"duration": 1
					},
					{
						"width": 128,
						"height": 128,
						"originX": 0.5,
						"originY": 0.5,
						"originalSource": "",
						"exportFormat": "png",
						"exportQuality": 0.8,
						"imageSpriteId": 7865565,
						"collisionPoly": {
							"points": [
								0.28125,
								0.28125,
								0.5,
								0.125,
								0.7177734375,
								0.28125,
								0.9052734375,
								0.5,
								0.7802734375,
								0.7802734375,
								0.5,
								0.7490234375,
								0.21875,
								0.7802734375,
								0.09375,
								0.5
							]
						},
						"useCollisionPoly": true,
						"duration": 1
					},
					{
						"width": 128,
						"height": 128,
						"originX": 0.5,
						"originY": 0.5,
						"originalSource": "",
						"exportFormat": "png",
						"exportQuality": 0.8,
						"imageSpriteId": 835191,
						"collisionPoly": {
							"points": [
								0.4375,
								0.4375,
								0.5,
								0.0625,
								0.7490234375,
								0.25,
								0.6865234375,
								0.5,
								0.6240234375,
								0.6240234375,
								0.5,
								0.8740234375,
								0.3125,
								0.6865234375,
								0.3125,
								0.5
							]
						},
						"useCollisionPoly": true,
						"duration": 1
					}
				],
				"sid": 685571629035323,
				"name": "Zombie_Attack",
				"isLooping": false,
				"isPingPong": false,
				"repeatCount": 1,
				"repeatTo": 0,
				"speed": 0
			},
			{
				"frames": [
					{
						"width": 256,
						"height": 256,
						"originX": 0.5,
						"originY": 0.5,
						"originalSource": "",
						"exportFormat": "png",
						"exportQuality": 0.8,
						"imageSpriteId": 406250,
						"collisionPoly": {
							"points": [
								0.109375,
								0.109375,
								0.5,
								0.1875,
								0.89013671875,
								0.109375,
								0.92138671875,
								0.5,
								0.90576171875,
								0.90576171875,
								0.5,
								0.90576171875,
								0.09375,
								0.90576171875,
								0.078125,
								0.5
							]
						},
						"useCollisionPoly": true,
						"duration": 1
					},
					{
						"width": 256,
						"height": 256,
						"originX": 0.5,
						"originY": 0.5,
						"originalSource": "",
						"exportFormat": "png",
						"exportQuality": 0.8,
						"imageSpriteId": 4817003,
						"collisionPoly": {
							"points": [
								0.109375,
								0.109375,
								0.5,
								0.1875,
								0.89013671875,
								0.109375,
								0.92138671875,
								0.5,
								0.90576171875,
								0.90576171875,
								0.5,
								0.90576171875,
								0.09375,
								0.90576171875,
								0.078125,
								0.5
							]
						},
						"useCollisionPoly": true,
						"duration": 1
					},
					{
						"width": 256,
						"height": 256,
						"originX": 0.5,
						"originY": 0.5,
						"originalSource": "",
						"exportFormat": "png",
						"exportQuality": 0.8,
						"imageSpriteId": 8777658,
						"collisionPoly": {
							"points": [
								0.109375,
								0.109375,
								0.5,
								0.1875,
								0.89013671875,
								0.109375,
								0.92138671875,
								0.5,
								0.90576171875,
								0.90576171875,
								0.5,
								0.90576171875,
								0.09375,
								0.90576171875,
								0.078125,
								0.5
							]
						},
						"useCollisionPoly": true,
						"duration": 1
					},
					{
						"width": 256,
						"height": 256,
						"originX": 0.5,
						"originY": 0.5,
						"originalSource": "",
						"exportFormat": "png",
						"exportQuality": 0.8,
						"imageSpriteId": 8503545,
						"collisionPoly": {
							"points": [
								0.109375,
								0.109375,
								0.5,
								0.1875,
								0.89013671875,
								0.109375,
								0.92138671875,
								0.5,
								0.90576171875,
								0.90576171875,
								0.5,
								0.90576171875,
								0.09375,
								0.90576171875,
								0.078125,
								0.5
							]
						},
						"useCollisionPoly": true,
						"duration": 1
					}
				],
				"sid": 580520557824995,
				"name": "Dragon_South",
				"isLooping": true,
				"isPingPong": false,
				"repeatCount": 1,
				"repeatTo": 0,
				"speed": 3
			},
			{
				"frames": [
					{
						"width": 256,
						"height": 256,
						"originX": 0.5,
						"originY": 0.5,
						"originalSource": "",
						"exportFormat": "png",
						"exportQuality": 0.8,
						"imageSpriteId": 5962948,
						"collisionPoly": {
							"points": [
								0.1875,
								0.1875,
								0.5,
								0.09375,
								0.74951171875,
								0.25,
								0.74951171875,
								0.5,
								0.74951171875,
								0.74951171875,
								0.5,
								0.93701171875,
								0.15625,
								0.84326171875,
								0.1875,
								0.5
							]
						},
						"useCollisionPoly": true,
						"duration": 1
					},
					{
						"width": 256,
						"height": 256,
						"originX": 0.5,
						"originY": 0.5,
						"originalSource": "",
						"exportFormat": "png",
						"exportQuality": 0.8,
						"imageSpriteId": 4793052,
						"collisionPoly": {
							"points": [
								0.1875,
								0.1875,
								0.5,
								0.09375,
								0.74951171875,
								0.25,
								0.74951171875,
								0.5,
								0.74951171875,
								0.74951171875,
								0.5,
								0.96826171875,
								0.15625,
								0.84326171875,
								0.1875,
								0.5
							]
						},
						"useCollisionPoly": true,
						"duration": 1
					},
					{
						"width": 256,
						"height": 256,
						"originX": 0.5,
						"originY": 0.5,
						"originalSource": "",
						"exportFormat": "png",
						"exportQuality": 0.8,
						"imageSpriteId": 6221083,
						"collisionPoly": {
							"points": [
								0.1875,
								0.1875,
								0.5,
								0.09375,
								0.74951171875,
								0.25,
								0.74951171875,
								0.5,
								0.74951171875,
								0.74951171875,
								0.5,
								0.93701171875,
								0.15625,
								0.84326171875,
								0.1875,
								0.5
							]
						},
						"useCollisionPoly": true,
						"duration": 1
					},
					{
						"width": 256,
						"height": 256,
						"originX": 0.5,
						"originY": 0.5,
						"originalSource": "",
						"exportFormat": "png",
						"exportQuality": 0.8,
						"imageSpriteId": 8452338,
						"collisionPoly": {
							"points": [
								0.1875,
								0.1875,
								0.5,
								0.09375,
								0.74951171875,
								0.25,
								0.74951171875,
								0.5,
								0.74951171875,
								0.74951171875,
								0.5,
								0.96826171875,
								0.15625,
								0.84326171875,
								0.1875,
								0.5
							]
						},
						"useCollisionPoly": true,
						"duration": 1
					}
				],
				"sid": 141243030579778,
				"name": "Dragon_East",
				"isLooping": true,
				"isPingPong": false,
				"repeatCount": 1,
				"repeatTo": 0,
				"speed": 3
			},
			{
				"frames": [
					{
						"width": 256,
						"height": 256,
						"originX": 0.5,
						"originY": 0.5,
						"originalSource": "",
						"exportFormat": "png",
						"exportQuality": 0.8,
						"imageSpriteId": 6545983,
						"collisionPoly": {
							"points": [
								0.109375,
								0.109375,
								0.5,
								0.1875,
								0.89013671875,
								0.109375,
								0.92138671875,
								0.5,
								0.90576171875,
								0.90576171875,
								0.5,
								0.90576171875,
								0.09375,
								0.90576171875,
								0.078125,
								0.5
							]
						},
						"useCollisionPoly": true,
						"duration": 1
					},
					{
						"width": 256,
						"height": 256,
						"originX": 0.5,
						"originY": 0.5,
						"originalSource": "",
						"exportFormat": "png",
						"exportQuality": 0.8,
						"imageSpriteId": 2710099,
						"collisionPoly": {
							"points": [
								0.109375,
								0.109375,
								0.5,
								0.1875,
								0.89013671875,
								0.109375,
								0.92138671875,
								0.5,
								0.90576171875,
								0.90576171875,
								0.5,
								0.90576171875,
								0.09375,
								0.90576171875,
								0.078125,
								0.5
							]
						},
						"useCollisionPoly": true,
						"duration": 1
					},
					{
						"width": 256,
						"height": 256,
						"originX": 0.5,
						"originY": 0.5,
						"originalSource": "",
						"exportFormat": "png",
						"exportQuality": 0.8,
						"imageSpriteId": 5995783,
						"collisionPoly": {
							"points": [
								0.109375,
								0.109375,
								0.5,
								0.1875,
								0.89013671875,
								0.109375,
								0.92138671875,
								0.5,
								0.90576171875,
								0.90576171875,
								0.5,
								0.90576171875,
								0.09375,
								0.90576171875,
								0.078125,
								0.5
							]
						},
						"useCollisionPoly": true,
						"duration": 1
					},
					{
						"width": 256,
						"height": 256,
						"originX": 0.5,
						"originY": 0.5,
						"originalSource": "",
						"exportFormat": "png",
						"exportQuality": 0.8,
						"imageSpriteId": 6350037,
						"collisionPoly": {
							"points": [
								0.109375,
								0.109375,
								0.5,
								0.1875,
								0.89013671875,
								0.109375,
								0.92138671875,
								0.5,
								0.90576171875,
								0.90576171875,
								0.5,
								0.90576171875,
								0.09375,
								0.90576171875,
								0.078125,
								0.5
							]
						},
						"useCollisionPoly": true,
						"duration": 1
					}
				],
				"sid": 954864559303826,
				"name": "Dragon_North",
				"isLooping": true,
				"isPingPong": false,
				"repeatCount": 1,
				"repeatTo": 0,
				"speed": 3
			},
			{
				"frames": [
					{
						"width": 256,
						"height": 256,
						"originX": 0.5,
						"originY": 0.5,
						"originalSource": "",
						"exportFormat": "png",
						"exportQuality": 0.8,
						"imageSpriteId": 8478619,
						"collisionPoly": {
							"points": [
								0.1875,
								0.1875,
								0.5,
								0.09375,
								0.74951171875,
								0.25,
								0.74951171875,
								0.5,
								0.74951171875,
								0.74951171875,
								0.5,
								0.93701171875,
								0.15625,
								0.84326171875,
								0.1875,
								0.5
							]
						},
						"useCollisionPoly": true,
						"duration": 1
					},
					{
						"width": 256,
						"height": 256,
						"originX": 0.5,
						"originY": 0.5,
						"originalSource": "",
						"exportFormat": "png",
						"exportQuality": 0.8,
						"imageSpriteId": 9407499,
						"collisionPoly": {
							"points": [
								0.1875,
								0.1875,
								0.5,
								0.09375,
								0.74951171875,
								0.25,
								0.74951171875,
								0.5,
								0.74951171875,
								0.74951171875,
								0.5,
								0.96826171875,
								0.15625,
								0.84326171875,
								0.1875,
								0.5
							]
						},
						"useCollisionPoly": true,
						"duration": 1
					},
					{
						"width": 256,
						"height": 256,
						"originX": 0.5,
						"originY": 0.5,
						"originalSource": "",
						"exportFormat": "png",
						"exportQuality": 0.8,
						"imageSpriteId": 4691163,
						"collisionPoly": {
							"points": [
								0.1875,
								0.1875,
								0.5,
								0.09375,
								0.74951171875,
								0.25,
								0.74951171875,
								0.5,
								0.74951171875,
								0.74951171875,
								0.5,
								0.93701171875,
								0.15625,
								0.84326171875,
								0.1875,
								0.5
							]
						},
						"useCollisionPoly": true,
						"duration": 1
					},
					{
						"width": 256,
						"height": 256,
						"originX": 0.5,
						"originY": 0.5,
						"originalSource": "",
						"exportFormat": "png",
						"exportQuality": 0.8,
						"imageSpriteId": 8203955,
						"collisionPoly": {
							"points": [
								0.1875,
								0.1875,
								0.5,
								0.09375,
								0.74951171875,
								0.25,
								0.74951171875,
								0.5,
								0.74951171875,
								0.74951171875,
								0.5,
								0.96826171875,
								0.15625,
								0.84326171875,
								0.1875,
								0.5
							]
						},
						"useCollisionPoly": true,
						"duration": 1
					}
				],
				"sid": 639546468598871,
				"name": "Dragon_West",
				"isLooping": true,
				"isPingPong": false,
				"repeatCount": 1,
				"repeatTo": 0,
				"speed": 3
			},
			{
				"frames": [
					{
						"width": 256,
						"height": 256,
						"originX": 0.5,
						"originY": 0.5,
						"originalSource": "",
						"exportFormat": "png",
						"exportQuality": 0.8,
						"imageSpriteId": 4862480,
						"collisionPoly": {
							"points": [
								0.109375,
								0.109375,
								0.5,
								0.1875,
								0.89013671875,
								0.109375,
								0.92138671875,
								0.5,
								0.90576171875,
								0.90576171875,
								0.5,
								0.90576171875,
								0.09375,
								0.90576171875,
								0.078125,
								0.5
							]
						},
						"useCollisionPoly": true,
						"duration": 1
					},
					{
						"width": 256,
						"height": 256,
						"originX": 0.5,
						"originY": 0.5,
						"originalSource": "",
						"exportFormat": "png",
						"exportQuality": 0.8,
						"imageSpriteId": 4003318,
						"collisionPoly": {
							"points": [
								0.1875,
								0.1875,
								0.5,
								0.09375,
								0.74951171875,
								0.25,
								0.74951171875,
								0.5,
								0.74951171875,
								0.74951171875,
								0.5,
								0.93701171875,
								0.15625,
								0.84326171875,
								0.1875,
								0.5
							]
						},
						"useCollisionPoly": true,
						"duration": 1
					},
					{
						"width": 256,
						"height": 256,
						"originX": 0.5,
						"originY": 0.5,
						"originalSource": "",
						"exportFormat": "png",
						"exportQuality": 0.8,
						"imageSpriteId": 344789,
						"collisionPoly": {
							"points": [
								0.109375,
								0.109375,
								0.5,
								0.1875,
								0.89013671875,
								0.109375,
								0.92138671875,
								0.5,
								0.90576171875,
								0.90576171875,
								0.5,
								0.90576171875,
								0.09375,
								0.90576171875,
								0.078125,
								0.5
							]
						},
						"useCollisionPoly": true,
						"duration": 1
					},
					{
						"width": 256,
						"height": 256,
						"originX": 0.5,
						"originY": 0.5,
						"originalSource": "",
						"exportFormat": "png",
						"exportQuality": 0.8,
						"imageSpriteId": 4728156,
						"collisionPoly": {
							"points": [
								0.8125,
								0.5,
								0.84375,
								0.84326171875,
								0.5,
								0.93701171875,
								0.25048828125,
								0.74951171875,
								0.25048828125,
								0.5,
								0.25048828125,
								0.25,
								0.5,
								0.09375,
								0.8125,
								0.1875
							]
						},
						"useCollisionPoly": true,
						"duration": 1
					}
				],
				"sid": 838177239983942,
				"name": "Dragon_Charge",
				"isLooping": false,
				"isPingPong": false,
				"repeatCount": 1,
				"repeatTo": 0,
				"speed": 0
			},
			{
				"frames": [
					{
						"width": 256,
						"height": 256,
						"originX": 0.5,
						"originY": 0.5,
						"originalSource": "",
						"exportFormat": "png",
						"exportQuality": 0.8,
						"imageSpriteId": 9093637,
						"collisionPoly": {
							"points": [
								0.109375,
								0.109375,
								0.5,
								0.1875,
								0.89013671875,
								0.109375,
								0.92138671875,
								0.5,
								0.93701171875,
								0.93701171875,
								0.5,
								0.99951171875,
								0.0625,
								0.93701171875,
								0.078125,
								0.5
							]
						},
						"useCollisionPoly": true,
						"duration": 1
					},
					{
						"width": 256,
						"height": 256,
						"originX": 0.5,
						"originY": 0.5,
						"originalSource": "",
						"exportFormat": "png",
						"exportQuality": 0.8,
						"imageSpriteId": 2249255,
						"collisionPoly": {
							"points": [
								0.1875,
								0.1875,
								0.5,
								0.09375,
								0.74951171875,
								0.25,
								0.84326171875,
								0.5,
								0.96826171875,
								0.96826171875,
								0.5,
								0.93701171875,
								0.15625,
								0.84326171875,
								0.1875,
								0.5
							]
						},
						"useCollisionPoly": true,
						"duration": 1
					},
					{
						"width": 256,
						"height": 256,
						"originX": 0.5,
						"originY": 0.5,
						"originalSource": "",
						"exportFormat": "png",
						"exportQuality": 0.8,
						"imageSpriteId": 8407145,
						"collisionPoly": {
							"points": [
								0.109375,
								0.109375,
								0.5,
								0.1875,
								0.89013671875,
								0.109375,
								0.92138671875,
								0.5,
								0.93701171875,
								0.93701171875,
								0.5,
								0.99951171875,
								0.0625,
								0.93701171875,
								0.078125,
								0.5
							]
						},
						"useCollisionPoly": true,
						"duration": 1
					},
					{
						"width": 256,
						"height": 256,
						"originX": 0.5,
						"originY": 0.5,
						"originalSource": "",
						"exportFormat": "png",
						"exportQuality": 0.8,
						"imageSpriteId": 5192953,
						"collisionPoly": {
							"points": [
								0.8125,
								0.5,
								0.84375,
								0.84326171875,
								0.5,
								0.93701171875,
								0.03173828125,
								0.96826171875,
								0.15673828125,
								0.5,
								0.25048828125,
								0.25,
								0.5,
								0.09375,
								0.8125,
								0.1875
							]
						},
						"useCollisionPoly": true,
						"duration": 1
					}
				],
				"sid": 850320891985898,
				"name": "Dragon_Attack",
				"isLooping": false,
				"isPingPong": false,
				"repeatCount": 1,
				"repeatTo": 0,
				"speed": 0
			}
		],
		"subfolders": []
	}
}